wkdaily/__init__.py
wkdaily/log_utils.py
wkdaily/server.py
wkdaily-1.2.0.dist-info/METADATA
wkdaily-1.2.0.dist-info/WHEEL
wkdaily-1.2.0.dist-info/entry_points.txt
wkdaily-1.2.0.dist-info/top_level.txt
wkdaily-1.2.0.dist-info/RECORD
